strappa/__init__.py
strappa/cli.py
strappa/main.py
strappa/utils.py
strappa-0.1.dist-info/METADATA
strappa-0.1.dist-info/WHEEL
strappa-0.1.dist-info/entry_points.txt
strappa-0.1.dist-info/top_level.txt
strappa-0.1.dist-info/RECORD
