Metadata-Version: 2.1
Name: strappa
Version: 0.1
Summary: A Python bootstrapper to help set up Python projects easily and faster
Home-page: https://github.com/buabaj/strappa
Author: jerry buaba
Author-email: buabajerry+strappa@gmail.com
Classifier: Development Status :: 3 - Alpha
Classifier: Intended Audience :: Developers
Classifier: License :: OSI Approved :: MIT License
Classifier: Programming Language :: Python :: 3
Classifier: Programming Language :: Python :: 3.8
Requires-Dist: click
Provides-Extra: dev
Requires-Dist: pytest ; extra == 'dev'
Requires-Dist: ruff ; extra == 'dev'
Requires-Dist: mypy ; extra == 'dev'
Requires-Dist: pytest-cov ; extra == 'dev'
